.travis.yml
CHANGELOG.rst
MANIFEST.in
README.rst
VERSION
requirements-test.txt
requirements.txt
setup.cfg
setup.py
guillotina_numpy/__init__.py
guillotina_numpy/field.py
guillotina_numpy/interfaces.py
guillotina_numpy/reader.py
guillotina_numpy/writer.py
guillotina_numpy.egg-info/PKG-INFO
guillotina_numpy.egg-info/SOURCES.txt
guillotina_numpy.egg-info/dependency_links.txt
guillotina_numpy.egg-info/requires.txt
guillotina_numpy.egg-info/top_level.txt
guillotina_numpy.egg-info/zip-safe
guillotina_numpy/tests/__init__.py
guillotina_numpy/tests/conftest.py
guillotina_numpy/tests/fixtures.py
guillotina_numpy/tests/test_field.py