Metadata-Version: 1.1
Name: guillotina-numpy
Version: 1.0.1
Summary: UNKNOWN
Home-page: https://github.com/guillotinaweb/guillotina_numpy.git
Author: Ramon Navarro Bosch
Author-email: ramon@flaps.io
License: BSD
Platform: UNKNOWN
Classifier: Development Status :: 4 - Beta
Classifier: Programming Language :: Python :: 3.7
Classifier: Topic :: Software Development :: Libraries :: Python Modules
